asdk_plugin_clients/__init__.py
asdk_plugin_clients/api_registry.py
asdk_plugin_clients/domain_apis_list.json
asdk_plugin_clients/agraph/__init__.py
asdk_plugin_clients/agraph/clients/__init__.py
asdk_plugin_clients/agraph/clients/capital_flows/__init__.py
asdk_plugin_clients/agraph/clients/capital_flows/enriched_capital_flow/__init__.py
asdk_plugin_clients/agraph/clients/capital_flows/enriched_capital_flow/v1/__init__.py
asdk_plugin_clients/agraph/clients/capital_flows/enriched_capital_flow/v1/EnrichedCapitalFlowAPI/__init__.py
asdk_plugin_clients/agraph/clients/capital_flows/enriched_capital_flow/v1/EnrichedCapitalFlowAPI/api_client.py
asdk_plugin_clients/agraph/clients/capital_flows/enriched_capital_flow/v1/EnrichedCapitalFlowAPI/api_response.py
asdk_plugin_clients/agraph/clients/capital_flows/enriched_capital_flow/v1/EnrichedCapitalFlowAPI/configuration.py
asdk_plugin_clients/agraph/clients/capital_flows/enriched_capital_flow/v1/EnrichedCapitalFlowAPI/exceptions.py
asdk_plugin_clients/agraph/clients/capital_flows/enriched_capital_flow/v1/EnrichedCapitalFlowAPI/rest.py
asdk_plugin_clients/agraph/clients/capital_flows/enriched_capital_flow/v1/EnrichedCapitalFlowAPI/swagger.json
asdk_plugin_clients/agraph/clients/capital_flows/enriched_capital_flow/v1/EnrichedCapitalFlowAPI/api/__init__.py
asdk_plugin_clients/agraph/clients/capital_flows/enriched_capital_flow/v1/EnrichedCapitalFlowAPI/api/default_enriched_capital_flow_api.py
asdk_plugin_clients/agraph/clients/capital_flows/enriched_capital_flow/v1/EnrichedCapitalFlowAPI/models/__init__.py
asdk_plugin_clients/agraph/clients/capital_flows/enriched_capital_flow/v1/EnrichedCapitalFlowAPI/models/any.py
asdk_plugin_clients/agraph/clients/capital_flows/enriched_capital_flow/v1/EnrichedCapitalFlowAPI/models/enriched_capital_flow_api_transition_enriched_capital_flow400_response.py
asdk_plugin_clients/agraph/clients/capital_flows/enriched_capital_flow/v1/EnrichedCapitalFlowAPI/models/enums_action.py
asdk_plugin_clients-2.0.0b2.dist-info/METADATA
asdk_plugin_clients-2.0.0b2.dist-info/WHEEL
asdk_plugin_clients-2.0.0b2.dist-info/top_level.txt
asdk_plugin_clients-2.0.0b2.dist-info/RECORD
