Metadata-Version: 2.1
Name: asdk_plugin_clients
Version: 2.0.0b2
Summary: AladdinSDK Plugin - asdk_plugin_clients
Classifier: Programming Language :: Python :: 3
Classifier: License :: OSI Approved :: Apache Software License
Classifier: Operating System :: OS Independent
Requires-Python: >=3.9
Requires-Dist: python-dateutil >=2.5.3
Requires-Dist: setuptools >=21.0.0
Requires-Dist: urllib3 >=1.25.3
Requires-Dist: pydantic <2,>=1.10.5
Requires-Dist: aenum >=3.1.11
